ansari/__init__.py
ansari/ansari_db.py
ansari/ansari_logger.py
ansari/config.py
ansari/agents/__init__.py
ansari/agents/ansari.py
ansari/agents/ansari_claude.py
ansari/agents/ansari_workflow.py
ansari/app/__init__.py
ansari/app/main_api.py
ansari/app/main_api_client.py
ansari/app/main_discord.py
ansari/app/main_file.py
ansari/app/main_stdio.py
ansari/app/main_whatsapp.py
ansari/cli/__init__.py
ansari/cli/query_api.py
ansari/cli/use_tools.py
ansari/examples/test_citations.py
ansari/examples/test_search_mawsuah.py
ansari/presenters/api_presenter.py
ansari/presenters/ayah_file_presenter.py
ansari/presenters/discord_presenter.py
ansari/presenters/file_presenter.py
ansari/presenters/gradio_presenter.py
ansari/presenters/stdio_presenter.py
ansari/presenters/whatsapp_presenter.py
ansari/resources/prompts/greeting.txt
ansari/resources/prompts/news.txt
ansari/resources/prompts/system_msg_ayah.txt
ansari/resources/prompts/system_msg_ayah_lay.txt
ansari/resources/prompts/system_msg_claude.txt
ansari/resources/prompts/system_msg_tool.txt
ansari/resources/templates/ask_question.txt
ansari/resources/templates/password_reset.html
ansari/tools/__init__.py
ansari/tools/base_search.py
ansari/tools/search_hadith.py
ansari/tools/search_mawsuah.py
ansari/tools/search_quran.py
ansari/tools/search_tafsir_encyc.py
ansari/tools/search_usul.py
ansari/tools/search_vectara.py
ansari/util/__init__.py
ansari/util/general_helpers.py
ansari/util/prompt_mgr.py
ansari/util/translation.py
ansari_backend-0.1.0.dist-info/LICENSE
ansari_backend-0.1.0.dist-info/METADATA
ansari_backend-0.1.0.dist-info/WHEEL
ansari_backend-0.1.0.dist-info/entry_points.txt
ansari_backend-0.1.0.dist-info/top_level.txt
ansari_backend-0.1.0.dist-info/RECORD
