Metadata-Version: 2.2
Name: ansari-backend
Version: 0.1.0
Summary: Ansari is an AI assistant to enhance understanding and practice of Islam.
Author-email: Ansari Project <feedback@ansari.chat>
License: MIT
Project-URL: Homepage, https://github.com/ansari-project/ansari-backend
Project-URL: Documentation, https://github.com/ansari-project/ansari-backend
Project-URL: Source, https://github.com/ansari-project/ansari-backend
Project-URL: Tracker, https://github.com/ansari-project/ansari-backend/issues
Classifier: Development Status :: 4 - Beta
Classifier: Intended Audience :: Developers
Classifier: License :: OSI Approved :: MIT License
Classifier: Programming Language :: Python :: 3
Classifier: Programming Language :: Python :: 3.8
Classifier: Programming Language :: Python :: 3.9
Classifier: Programming Language :: Python :: 3.10
Classifier: Topic :: Software Development :: Libraries
Requires-Python: >=3.8
License-File: LICENSE
Requires-Dist: bcrypt
Requires-Dist: diskcache
Requires-Dist: email-validator
Requires-Dist: fastapi
Requires-Dist: jinja2
Requires-Dist: langdetect
Requires-Dist: litellm<1.59.9,>=1.59.6
Requires-Dist: loguru
Requires-Dist: openai
Requires-Dist: pandas
Requires-Dist: psycopg2-binary
Requires-Dist: pydantic_settings
Requires-Dist: pyjwt
Requires-Dist: rich
Requires-Dist: sendgrid
Requires-Dist: sentry-sdk[fastapi]
Requires-Dist: tenacity
Requires-Dist: tiktoken
Requires-Dist: typer
Requires-Dist: uvicorn
Requires-Dist: zxcvbn
Requires-Dist: anthropic
